cliqestim/__init__.py
cliqestim/cli.cpython-311-darwin.so
cliqestim-1.1.0.dist-info/LICENCE.txt
cliqestim-1.1.0.dist-info/METADATA
cliqestim-1.1.0.dist-info/WHEEL
cliqestim-1.1.0.dist-info/top_level.txt
cliqestim-1.1.0.dist-info/RECORD
