Metadata-Version: 2.1
Name: cliqestim
Version: 1.1.0
Summary: A package for estimating clique structure
Author: Gongruihao
Author-email: 202031200039@mail.bnu.edu.cn
Classifier: Programming Language :: Python :: 3
Classifier: Programming Language :: Python :: 3.7
Classifier: Programming Language :: Python :: 3.8
Classifier: Programming Language :: Python :: 3.9
License-File: LICENCE.txt
Requires-Dist: cdlib
